{
  "AIInput": {
    "data": [
      {
        "component": "AIInput",
        "uid": "input-004",
        "purpose": "readonly",
        "placeholder": "GarbaGE",
        "type": "readonly"
      },
      {
        "component": "AIInput",
        "uid": "input-002",
        "purpose": "CollectUserFirstName",
        "placeholder": "Firstname",
        "value": "firstnameValue",
        "onChange": "[complex expression not resolved]"
      },
      {
        "component": "AIInput",
        "uid": "input-003",
        "purpose": "collectUserLastName",
        "placeholder": "Lastname",
        "value": "lastnameValue",
        "onChange": "[complex expression not resolved]"
      },
      {
        "component": "AIInput",
        "uid": "input-001",
        "purpose": "collectUserEmail",
        "placeholder": "name@example.com",
        "value": "emailValue",
        "onChange": "[complex expression not resolved]"
      }
    ]
  },
  "AIButton": {
    "data": [
      {
        "component": "AIButton",
        "uid": "btn-001",
        "purpose": "submitForm",
        "onClick": "[complex expression not resolved]",
        "label": "Submit"
      },
      {
        "component": "AIButton",
        "uid": "btn-002",
        "purpose": "cancel",
        "onClick": "[complex expression not resolved]",
        "label": "Cancel"
      }
    ]
  }
}